brachinus/__init__.py
brachinus/__main__.py
brachinus/cli.py
brachinus/version.py
brachinus-1.2.0.dist-info/licenses/LICENSE
brachinus-1.2.0.dist-info/METADATA
brachinus-1.2.0.dist-info/WHEEL
brachinus-1.2.0.dist-info/entry_points.txt
brachinus-1.2.0.dist-info/top_level.txt
brachinus-1.2.0.dist-info/RECORD
