Metadata-Version: 2.4
Name: brachinus
Version: 1.2.0
Summary: AES-256 CBC file encryption library with support for individual files and directory batch operations.
Author-email: Juan Bindez <juanbindez780@gmail.com>
License: GPLv2 license
Project-URL: Homepage, https://github.com/juanbindez/brachinus
Project-URL: Bug Reports, https://github.com/juanbindez/brachinus/issues
Project-URL: Read the Docs, http://brachinus.readthedocs.io/
Keywords: encryption,crypto,aes,security,files,cryptography,aes-256,file-protection,data-security
Classifier: Development Status :: 5 - Production/Stable
Classifier: Environment :: Console
Classifier: Intended Audience :: Developers
Classifier: License :: OSI Approved :: GNU General Public License v2 (GPLv2)
Classifier: Natural Language :: English
Classifier: Operating System :: OS Independent
Classifier: Programming Language :: Python :: 3.8
Classifier: Programming Language :: Python :: 3.9
Classifier: Programming Language :: Python :: 3.10
Classifier: Programming Language :: Python :: 3.11
Classifier: Programming Language :: Python :: 3.12
Classifier: Programming Language :: Python
Classifier: Topic :: Security :: Cryptography
Classifier: Topic :: Software Development :: Libraries :: Python Modules
Classifier: Topic :: Terminals
Classifier: Topic :: System :: Filesystems
Classifier: Topic :: Utilities
Requires-Python: >=3.7
License-File: LICENSE
Requires-Dist: pycryptodome
Requires-Dist: tqdm
Dynamic: license-file
